{
"companyName": "DefaultCompany",
"productName": "webgl",
"productVersion": "0.1",
"dataUrl": "testgamma2.data.unityweb",
"wasmCodeUrl": "testgamma2.wasm.code.unityweb",
"wasmFrameworkUrl": "testgamma2.wasm.framework.unityweb",
"graphicsAPI": ["WebGL 2.0","WebGL 1.0"],
"webglContextAttributes": {"preserveDrawingBuffer": false},
"splashScreenStyle": "Dark",
"backgroundColor": "#231F20",
"cacheControl": {"default": "must-revalidate"},
"developmentBuild": false,
"multithreading": false,
"unityVersion": "2019.3.5f1"
}